CHANGELOG.md
COPYING.txt
MANIFEST.in
README.rst
setup.py
rattail_woocommerce/__init__.py
rattail_woocommerce/_version.py
rattail_woocommerce/commands.py
rattail_woocommerce/config.py
rattail_woocommerce.egg-info/PKG-INFO
rattail_woocommerce.egg-info/SOURCES.txt
rattail_woocommerce.egg-info/dependency_links.txt
rattail_woocommerce.egg-info/entry_points.txt
rattail_woocommerce.egg-info/not-zip-safe
rattail_woocommerce.egg-info/requires.txt
rattail_woocommerce.egg-info/top_level.txt
rattail_woocommerce/datasync/__init__.py
rattail_woocommerce/datasync/woocommerce.py
rattail_woocommerce/db/__init__.py
rattail_woocommerce/db/model.py
rattail_woocommerce/db/alembic/versions/c0bcca7bd1f9_initial_woo_related_tables.py
rattail_woocommerce/importing/__init__.py
rattail_woocommerce/importing/model.py
rattail_woocommerce/importing/versions.py
rattail_woocommerce/importing/woocommerce.py
rattail_woocommerce/woocommerce/__init__.py
rattail_woocommerce/woocommerce/importing/__init__.py
rattail_woocommerce/woocommerce/importing/model.py
rattail_woocommerce/woocommerce/importing/rattail.py